{
  "artifact_id": "BM-0052",
  "model": "llama4-maverick",
  "method": "plain",
  "checkov_rule_id": "CKV_AWS_315",
  "violation_class": "public_exposure",
  "v1_syntax_valid": true,
  "v2_target_resolved": false,
  "v3_new_issues_count": 0,
  "v4_lines_changed": 40,
  "v4_diff_ratio": 0.7143,
  "overall_verified_fix": false,
  "num_attempts": 1,
  "input_tokens": 569,
  "output_tokens": 212,
  "latency_seconds": 0.99,
  "error": "",
  "attempts": [
    {
      "attempt": 1,
      "response": "resource \"aws_launch_configuration\" \"safe_lc\" {\n  name          = \"safe-lc-${random_id.id.hex}\"\n  image_id      = \"ami-0c55b24b055c14ff6\" \n  instance_type = \"t2.micro\"\n  associate_public_ip_address = false \n}\n\nresource \"aws_autoscaling_group\" \"safe_asg\" {\n  name                 = \"safe-asg-${random_id.id.hex}\"\n  launch_configuration = aws_launch_configuration.safe_lc.name\n  min_size             = 1\n  max_size             = 3\n  desired_capacity   = 1\n  vpc_zone_identifier = [\"subnet-0bb1c79de3EXAMPLE\", \"subnet-0bb1c79de4EXAMPLE\"] \n\n\n  tags = [\n    {\n      key                 = \"Name\"\n      value               = \"SafeAutoScalingGroup\"\n      propagate_at_launch = true\n    },\n  ]\n}\n\nresource \"random_id\" \"id\" {\n  byte_length = 8\n}",
      "fixed_text": "resource \"aws_launch_configuration\" \"safe_lc\" {\n  name          = \"safe-lc-${random_id.id.hex}\"\n  image_id      = \"ami-0c55b24b055c14ff6\" \n  instance_type = \"t2.micro\"\n  associate_public_ip_address = false \n}\n\nresource \"aws_autoscaling_group\" \"safe_asg\" {\n  name                 = \"safe-asg-${random_id.id.hex}\"\n  launch_configuration = aws_launch_configuration.safe_lc.name\n  min_size             = 1\n  max_size             = 3\n  desired_capacity   = 1\n  vpc_zone_identifier = [\"subnet-0bb1c79de3EXAMPLE\", \"subnet-0bb1c79de4EXAMPLE\"] \n\n\n  tags = [\n    {\n      key                 = \"Name\"\n      value               = \"SafeAutoScalingGroup\"\n      propagate_at_launch = true\n    },\n  ]\n}\n\nresource \"random_id\" \"id\" {\n  byte_length = 8\n}",
      "verification": {
        "target_rule_id": "CKV_AWS_315",
        "v1_syntax_valid": true,
        "v1_syntax_detail": "Parsed successfully",
        "v2_target_resolved": false,
        "v2_resolution_detail": "Target rule CKV_AWS_315 still present in 3 failures",
        "v3_new_issues_count": 0,
        "v3_new_issues_list": [],
        "v4_minimality": {
          "lines_added": 6,
          "lines_removed": 34,
          "lines_changed": 40,
          "original_lines": 56,
          "repaired_lines": 28,
          "diff_ratio": 0.7143
        },
        "overall_verified_fix": false
      }
    }
  ]
}